src/fifo.v
/*
-------------------------MINI_Project---------------------------------------------
Write test cases for verifying the fifo who code is mentioned below. 

You need to create write task and read task inside the test bench and verify the 
design. Show the results after running the same in Modelsim/questa Simulation tool. 
*/
/////////////////////////////////////////////////////////////////////////////////// 
/*
//fifo memory 
  module fifo(clk, 
             rst_n, 
             wr,rd, 
             data_in,  
             data_out, 
             fifo_full, 
             fifo_empty); 
 
    parameter FIFO_WIDTH = 8; 
    parameter FIFO_DEPTH = 16; 
 
    input clk,rst_n,wr,rd; 
    input [FIFO_WIDTH-1:0]data_in; 
    output fifo_full,fifo_empty; 
    output [FIFO_WIDTH-1:0] data_out ; 
 
    reg [FIFO_WIDTH-1:0] data_out; 
 
    reg [FIFO_WIDTH-1:0]mem[FIFO_DEPTH-1:0]; // Memory Dec 
 
    reg [3:0]wr_ptr,rd_ptr,wr_rd_ptr_diff;  
    integer i; 
 
    reg [3:0]count,count1; 
 
 
    wire  fifo_full = (wr_ptr == 4'd0 & wr_rd_ptr_diff == 4'd14) ? 1 : 0; 
    wire  fifo_empty = (rd_ptr== 4'd0 & wr_rd_ptr_diff == 4'd0) ? 1 : 0; 
 
    always @ (posedge clk or negedge rst_n)begin 
        if(!rst_n) begin 
            for(i=0;i<=15;i=i+1) 
                mem[i]<=8'd0; 
        end 
        //WRITE PORTION 
        else if(wr) 
            mem[wr_ptr]<=data_in; 
    end 
 
    //Write Ptr 
    always @ (posedge clk or negedge rst_n) begin 
        if(!rst_n) 
            wr_ptr <= 4'd0; 
        else if(wr) 
            wr_ptr <= wr_ptr + 4'd1;   
    end 
 
    //READ OPERATION 
    always @ (posedge clk or negedge rst_n) begin 
        if(!rst_n) 
            data_out <= 8'd0; 
        else if(rd) 
            data_out <= mem[rd_ptr]; 
    end 
 
    //Read Ptr 
    always @ (posedge clk or negedge rst_n) begin 
        if(!rst_n) 
            rd_ptr <= 4'd0; 
        else if(rd) 
            rd_ptr <= rd_ptr + 4'd1; 
    end 
    //FIFO EMPTY and FULL Logic 
    always @ (posedge clk or negedge rst_n) begin 
        if(!rst_n) 
            wr_rd_ptr_diff <= 4'd0; 
        else if(wr &  wr_rd_ptr_diff !=4'd15) 
            wr_rd_ptr_diff <= wr_rd_ptr_diff + 4'd1; 
        else if(rd & wr_rd_ptr_diff != 4'd0) 
            wr_rd_ptr_diff <= wr_rd_ptr_diff - 4'd1; 
    end 
endmodule
*/

/*
//////////////////////////////////////////////////////////////////////////////////
Here are few of the design errors found in the design fifo.v :
1] the full condition logic i.e. wire fifo_full = (wr_ptr == 4'd0 & wr_rd_ptr_diff == 4'd14) ? 1 : 0; 
because a FIFO of depth 16 should detect full based on occupancy count reaching its maximum, not based on a specific
 pointer value combined with a difference of 14, so this condition does not correctly represent 
 the full state and therefore full is never asserted when 16 elements are written.
 
2]the write operation is not protected against overflow since else if(wr) mem[wr_ptr] <= data_in; 
without checking fifo_full, which allows new data to overwrite existing data when the FIFO is already full, 
causing corruption and mismatch during reads.

3]the read operation is not protected against underflow because  else if(rd) data_out <= mem[rd_ptr]; 
without checking fifo_empty, so the design continues to read and increment the read pointer even when 
no valid data is stored, which leads to invalid outputs and scoreboard errors.

4]the occupancy tracking logic 
else if(wr & wr_rd_ptr_diff !=4'd15) wr_rd_ptr_diff <= wr_rd_ptr_diff + 4'd1; 
else if(rd & wr_rd_ptr_diff != 4'd0) wr_rd_ptr_diff <= wr_rd_ptr_diff - 4'd1; 
because it does not correctly handle simultaneous read and write operations, 
and it artificially limits the maximum difference to 15 for a depth of 16, which results
 incorrect tracking of how many elements are actually stored.
 
5]the empty detection logic wire fifo_empty = (rd_ptr== 4'd0 & wr_rd_ptr_diff == 4'd0) ? 1 : 0; 
because emptiness should depend only on the occupancy count being zero, not on the read pointer being zero, 
since after pointer wrap-around the FIFO can be empty while rd_ptr is not zero, making this condition unreliable.


///////////////////////////////////////////////////////////////////////////////////
*/

module fifo (
    clk,
    rst_n,
    wr,
    rd,
    data_in,
    data_out,
    fifo_full,
    fifo_empty
);

parameter FIFO_WIDTH = 8;
parameter FIFO_DEPTH = 16;
parameter PTR_WIDTH  = 4;   // log2(16) = 4

input clk, rst_n;
input wr, rd;
input [FIFO_WIDTH-1:0] data_in;

output reg [FIFO_WIDTH-1:0] data_out;
output fifo_full, fifo_empty;

reg [FIFO_WIDTH-1:0] mem [0:FIFO_DEPTH-1];

reg [PTR_WIDTH-1:0] wr_ptr;
reg [PTR_WIDTH-1:0] rd_ptr;
reg [PTR_WIDTH:0]   count;     // 5-bit to count 0–16

integer i;

// --------------------------------------------------
// FULL and EMPTY Conditions
// --------------------------------------------------
assign fifo_full  = (count == FIFO_DEPTH);
assign fifo_empty = (count == 0);

// --------------------------------------------------
// MEMORY WRITE
// --------------------------------------------------
always @(posedge clk or negedge rst_n) begin
    if (!rst_n) begin
        for (i = 0; i < FIFO_DEPTH; i = i + 1)
            mem[i] <= 0;
    end
    else if (wr && !fifo_full) begin
        mem[wr_ptr] <= data_in;
    end
end

// --------------------------------------------------
// WRITE POINTER
// --------------------------------------------------
always @(posedge clk or negedge rst_n) begin
    if (!rst_n)
        wr_ptr <= 0;
    else if (wr && !fifo_full)
        wr_ptr <= wr_ptr + 1;
end

// --------------------------------------------------
// READ OPERATION
// --------------------------------------------------
always @(posedge clk or negedge rst_n) begin
    if (!rst_n)
        data_out <= 0;
    else if (rd && !fifo_empty)
        data_out <= mem[rd_ptr];
end

// --------------------------------------------------
// READ POINTER
// --------------------------------------------------
always @(posedge clk or negedge rst_n) begin
    if (!rst_n)
        rd_ptr <= 0;
    else if (rd && !fifo_empty)
        rd_ptr <= rd_ptr + 1;
end

// --------------------------------------------------
// COUNT LOGIC (Handles simultaneous read/write)
// --------------------------------------------------
always @(posedge clk or negedge rst_n) begin
    if (!rst_n)
        count <= 0;
    else begin
        case ({wr && !fifo_full, rd && !fifo_empty})
            2'b10: count <= count + 1;   // write only
            2'b01: count <= count - 1;   // read only
            2'b11: count <= count;       // simultaneous → no change
            default: count <= count;
        endcase
    end
end

endmodule
//*/

src/fifo_tb.v
`timescale 1ns/1ps

module fifo_tb;

parameter FIFO_WIDTH = 8;
parameter FIFO_DEPTH = 16;

reg clk;
reg rst_n;
reg wr, rd;
reg [FIFO_WIDTH-1:0] data_in;

wire [FIFO_WIDTH-1:0] data_out;
wire fifo_full;
wire fifo_empty;

// ------------------------------------------------
// Test Counters
// ------------------------------------------------
integer total_tests = 0;
integer passed_tests = 0;
integer failed_tests = 0;

// ------------------------------------------------
// Golden Reference Model (Independent of DUT)
// ------------------------------------------------
reg [FIFO_WIDTH-1:0] ref_mem [0:FIFO_DEPTH-1];
integer ref_wr_ptr = 0;
integer ref_rd_ptr = 0;
integer ref_count  = 0;

// ------------------------------------------------
// DUT
// ------------------------------------------------
fifo dut (
    .clk(clk),
    .rst_n(rst_n),
    .wr(wr),
    .rd(rd),
    .data_in(data_in),
    .data_out(data_out),
    .fifo_full(fifo_full),
    .fifo_empty(fifo_empty)
);

// ------------------------------------------------
// Clock
// ------------------------------------------------
always #5 clk = ~clk;

// ------------------------------------------------
// Waveform
// ------------------------------------------------
initial begin
    $dumpfile("fifo_dump.vcd");
    $dumpvars(0,fifo_tb);
end

// ------------------------------------------------
// Continuous Monitor
// ------------------------------------------------
always @(posedge clk) begin
    $display("T=%0t | WR=%b RD=%b | DIN=%0d | DOUT=%0d | REF_COUNT=%0d | DUT_FULL=%b DUT_EMPTY=%b",$time, wr, rd, data_in, data_out, ref_count, fifo_full, fifo_empty);
end

// ------------------------------------------------
// RESET
// ------------------------------------------------
task reset_fifo;
begin
    rst_n = 0;
    wr = 0;
    rd = 0;
    data_in = 0;
    #20;
    rst_n = 1;
    #20;
end
endtask

// ------------------------------------------------
// WRITE TASK (Reference + DUT)
// ------------------------------------------------
task write_fifo(input [7:0] data);
begin
    @(posedge clk);
    wr = 1;
    rd = 0;
    data_in = data;

    // Golden model update (independent of DUT full)
    if (ref_count < FIFO_DEPTH) begin
        ref_mem[ref_wr_ptr] = data;
        ref_wr_ptr = (ref_wr_ptr + 1) % FIFO_DEPTH;
        ref_count = ref_count + 1;
    end
    else begin
        $display("EXPECTED OVERFLOW (reference full)");
    end

    @(posedge clk);
    wr = 0;
end
endtask

// ------------------------------------------------
// READ TASK (Reference + Compare)
// ------------------------------------------------
task read_fifo;
reg [7:0] expected;
begin
    @(posedge clk);
    wr = 0;
    rd = 1;

    if (ref_count > 0) begin
        expected = ref_mem[ref_rd_ptr];
        ref_rd_ptr = (ref_rd_ptr + 1) % FIFO_DEPTH;
        ref_count = ref_count - 1;

        @(posedge clk);

        total_tests = total_tests + 1;

        if (data_out === expected) begin
            passed_tests = passed_tests + 1;
            $display("PASS: Expected=%0d Actual=%0d", expected, data_out);
        end
        else begin
            failed_tests = failed_tests + 1;
            $display("FAIL: Expected=%0d Actual=%0d", expected, data_out);
        end
    end
    else begin
        $display("EXPECTED UNDERFLOW (reference empty)");
        @(posedge clk);
    end

    rd = 0;
end
endtask

// ------------------------------------------------
// Manual 16 Write / 16 Read Test
// ------------------------------------------------
task manual_test;
integer i;
begin
    $display("\n===== MANUAL 16 WRITE / READ =====");

    for (i=0; i<16; i=i+1)
        write_fifo(i+10);   // Values: 10 to 25

    if (fifo_full)
        $display("DUT FULL asserted");
    else
        $display("DUT FULL NOT asserted (BUG)");

    for (i=0; i<16; i=i+1)
        read_fifo;

    if (fifo_empty)
        $display("DUT EMPTY asserted");
    else
        $display("DUT EMPTY NOT asserted (BUG)");

    $display("===== END MANUAL TEST =====\n");
end
endtask

// ------------------------------------------------
// Random Stress Test (200+ verified reads)
// ------------------------------------------------
task random_stress(input integer required_reads);
reg [7:0] rand_data;
reg rand_op;
begin
    $display("\n===== RANDOM STRESS START =====");

    while (total_tests < required_reads) begin
        @(posedge clk);
        rand_op = $random % 2;

        if (rand_op)
            write_fifo($random);
        else
            read_fifo;
    end

    $display("===== RANDOM STRESS END =====\n");
end
endtask

// ------------------------------------------------
// Initial Block
// ------------------------------------------------
initial begin
    clk = 0;

    reset_fifo;

    manual_test;

    random_stress(200);

    #50;

    $display("\n================================");
    $display("TOTAL TESTS  = %0d", total_tests);
    $display("PASSED TESTS = %0d", passed_tests);
    $display("FAILED TESTS = %0d", failed_tests);
    $display("================================\n");

    $finish;
end

endmodule

src/fifo_dump.vcd
$date
	Mon Feb 23 18:52:14 2026
$end
$version
	Icarus Verilog
$end
$timescale
	1ps
$end
$scope module fifo_tb $end
$var wire 1 ! fifo_full $end
$var wire 1 " fifo_empty $end
$var wire 8 # data_out [7:0] $end
$var parameter 32 $ FIFO_DEPTH $end
$var parameter 32 % FIFO_WIDTH $end
$var reg 1 & clk $end
$var reg 8 ' data_in [7:0] $end
$var reg 1 ( rd $end
$var reg 1 ) rst_n $end
$var reg 1 * wr $end
$var integer 32 + failed_tests [31:0] $end
$var integer 32 , passed_tests [31:0] $end
$var integer 32 - ref_count [31:0] $end
$var integer 32 . ref_rd_ptr [31:0] $end
$var integer 32 / ref_wr_ptr [31:0] $end
$var integer 32 0 total_tests [31:0] $end
$scope module dut $end
$var wire 1 & clk $end
$var wire 8 1 data_in [7:0] $end
$var wire 1 ( rd $end
$var wire 1 ) rst_n $end
$var wire 1 * wr $end
$var wire 1 ! fifo_full $end
$var wire 1 " fifo_empty $end
$var parameter 32 2 FIFO_DEPTH $end
$var parameter 32 3 FIFO_WIDTH $end
$var parameter 32 4 PTR_WIDTH $end
$var reg 5 5 count [4:0] $end
$var reg 8 6 data_out [7:0] $end
$var reg 4 7 rd_ptr [3:0] $end
$var reg 4 8 wr_ptr [3:0] $end
$var integer 32 9 i [31:0] $end
$upscope $end
$scope task manual_test $end
$var integer 32 : i [31:0] $end
$upscope $end
$scope task random_stress $end
$var reg 1 ; rand_op $end
$var integer 32 < required_reads [31:0] $end
$upscope $end
$scope task read_fifo $end
$var reg 8 = expected [7:0] $end
$upscope $end
$scope task reset_fifo $end
$upscope $end
$scope task write_fifo $end
$var reg 8 > data [7:0] $end
$upscope $end
$upscope $end
$enddefinitions $end
$comment Show the parameter values. $end
$dumpall
b100 4
b1000 3
b10000 2
b1000 %
b10000 $
$end
#0
$dumpvars
bx >
bx =
bx <
x;
bx :
b10000 9
b0 8
b0 7
b0 6
b0 5
b0 1
b0 0
b0 /
b0 .
b0 -
b0 ,
b0 +
0*
0)
0(
b0 '
0&
b0 #
1"
0!
$end
#5000
b10000 9
1&
#10000
0&
#15000
b10000 9
1&
#20000
0&
1)
#25000
1&
#30000
0&
#35000
1&
#40000
0&
b1010 >
b0 :
#45000
0"
b1 5
b1 8
b1 -
b1 /
b1010 '
b1010 1
1*
1&
#50000
0&
#55000
b1011 >
b1 :
0*
1&
#60000
0&
#65000
b10 5
b10 8
b10 -
b10 /
b1011 '
b1011 1
1*
1&
#70000
0&
#75000
b1100 >
b10 :
0*
1&
#80000
0&
#85000
b11 5
b11 8
b11 -
b11 /
b1100 '
b1100 1
1*
1&
#90000
0&
#95000
b1101 >
b11 :
0*
1&
#100000
0&
#105000
b100 5
b100 8
b100 -
b100 /
b1101 '
b1101 1
1*
1&
#110000
0&
#115000
b1110 >
b100 :
0*
1&
#120000
0&
#125000
b101 5
b101 8
b101 -
b101 /
b1110 '
b1110 1
1*
1&
#130000
0&
#135000
b1111 >
b101 :
0*
1&
#140000
0&
#145000
b110 5
b110 8
b110 -
b110 /
b1111 '
b1111 1
1*
1&
#150000
0&
#155000
b10000 >
b110 :
0*
1&
#160000
0&
#165000
b111 5
b111 8
b111 -
b111 /
b10000 '
b10000 1
1*
1&
#170000
0&
#175000
b10001 >
b111 :
0*
1&
#180000
0&
#185000
b1000 5
b1000 8
b1000 -
b1000 /
b10001 '
b10001 1
1*
1&
#190000
0&
#195000
b10010 >
b1000 :
0*
1&
#200000
0&
#205000
b1001 5
b1001 8
b1001 -
b1001 /
b10010 '
b10010 1
1*
1&
#210000
0&
#215000
b10011 >
b1001 :
0*
1&
#220000
0&
#225000
b1010 5
b1010 8
b1010 -
b1010 /
b10011 '
b10011 1
1*
1&
#230000
0&
#235000
b10100 >
b1010 :
0*
1&
#240000
0&
#245000
b1011 5
b1011 8
b1011 -
b1011 /
b10100 '
b10100 1
1*
1&
#250000
0&
#255000
b10101 >
b1011 :
0*
1&
#260000
0&
#265000
b1100 5
b1100 8
b1100 -
b1100 /
b10101 '
b10101 1
1*
1&
#270000
0&
#275000
b10110 >
b1100 :
0*
1&
#280000
0&
#285000
b1101 5
b1101 8
b1101 -
b1101 /
b10110 '
b10110 1
1*
1&
#290000
0&
#295000
b10111 >
b1101 :
0*
1&
#300000
0&
#305000
b1110 5
b1110 8
b1110 -
b1110 /
b10111 '
b10111 1
1*
1&
#310000
0&
#315000
b11000 >
b1110 :
0*
1&
#320000
0&
#325000
b1111 5
b1111 8
b1111 -
b1111 /
b11000 '
b11000 1
1*
1&
#330000
0&
#335000
b11001 >
b1111 :
0*
1&
#340000
0&
#345000
1!
b10000 5
b0 8
b10000 -
b0 /
b11001 '
b11001 1
1*
1&
#350000
0&
#355000
b0 :
0*
1&
#360000
0&
#365000
0!
b1111 5
b1 7
b1010 #
b1010 6
b1111 -
b1 .
b1010 =
1(
1&
#370000
0&
#375000
b1 :
0(
b1 ,
b1 0
1&
#380000
0&
#385000
b1110 5
b10 7
b1011 #
b1011 6
b1110 -
b10 .
b1011 =
1(
1&
#390000
0&
#395000
b10 :
0(
b10 ,
b10 0
1&
#400000
0&
#405000
b1101 5
b11 7
b1100 #
b1100 6
b1101 -
b11 .
b1100 =
1(
1&
#410000
0&
#415000
b11 :
0(
b11 ,
b11 0
1&
#420000
0&
#425000
b1100 5
b100 7
b1101 #
b1101 6
b1100 -
b100 .
b1101 =
1(
1&
#430000
0&
#435000
b100 :
0(
b100 ,
b100 0
1&
#440000
0&
#445000
b1011 5
b101 7
b1110 #
b1110 6
b1011 -
b101 .
b1110 =
1(
1&
#450000
0&
#455000
b101 :
0(
b101 ,
b101 0
1&
#460000
0&
#465000
b1010 5
b110 7
b1111 #
b1111 6
b1010 -
b110 .
b1111 =
1(
1&
#470000
0&
#475000
b110 :
0(
b110 ,
b110 0
1&
#480000
0&
#485000
b1001 5
b111 7
b10000 #
b10000 6
b1001 -
b111 .
b10000 =
1(
1&
#490000
0&
#495000
b111 :
0(
b111 ,
b111 0
1&
#500000
0&
#505000
b1000 5
b1000 7
b10001 #
b10001 6
b1000 -
b1000 .
b10001 =
1(
1&
#510000
0&
#515000
b1000 :
0(
b1000 ,
b1000 0
1&
#520000
0&
#525000
b111 5
b1001 7
b10010 #
b10010 6
b111 -
b1001 .
b10010 =
1(
1&
#530000
0&
#535000
b1001 :
0(
b1001 ,
b1001 0
1&
#540000
0&
#545000
b110 5
b1010 7
b10011 #
b10011 6
b110 -
b1010 .
b10011 =
1(
1&
#550000
0&
#555000
b1010 :
0(
b1010 ,
b1010 0
1&
#560000
0&
#565000
b101 5
b1011 7
b10100 #
b10100 6
b101 -
b1011 .
b10100 =
1(
1&
#570000
0&
#575000
b1011 :
0(
b1011 ,
b1011 0
1&
#580000
0&
#585000
b100 5
b1100 7
b10101 #
b10101 6
b100 -
b1100 .
b10101 =
1(
1&
#590000
0&
#595000
b1100 :
0(
b1100 ,
b1100 0
1&
#600000
0&
#605000
b11 5
b1101 7
b10110 #
b10110 6
b11 -
b1101 .
b10110 =
1(
1&
#610000
0&
#615000
b1101 :
0(
b1101 ,
b1101 0
1&
#620000
0&
#625000
b10 5
b1110 7
b10111 #
b10111 6
b10 -
b1110 .
b10111 =
1(
1&
#630000
0&
#635000
b1110 :
0(
b1110 ,
b1110 0
1&
#640000
0&
#645000
b1 5
b1111 7
b11000 #
b11000 6
b1 -
b1111 .
b11000 =
1(
1&
#650000
0&
#655000
b1111 :
0(
b1111 ,
b1111 0
1&
#660000
0&
#665000
1"
b0 5
b0 7
b11001 #
b11001 6
b0 -
b0 .
b11001 =
1(
1&
#670000
0&
#675000
b11001000 <
b10000 :
0(
b10000 ,
b10000 0
1&
#680000
0&
#685000
0;
1&
#690000
0&
#695000
1(
1&
#700000
0&
#705000
0(
1&
#710000
0&
#715000
b1001 >
1;
1&
#720000
0&
#725000
0"
b1 5
b1 8
b1 -
b1 /
b1001 '
b1001 1
1*
1&
#730000
0&
#735000
0*
1&
#740000
0&
#745000
b1101 >
1&
#750000
0&
#755000
b10 8
b10 5
b10 -
b10 /
b1101 '
b1101 1
1*
1&
#760000
0&
#765000
0*
1&
#770000
0&
#775000
b1100101 >
1&
#780000
0&
#785000
b11 5
b11 8
b11 -
b11 /
b1100101 '
b1100101 1
1*
1&
#790000
0&
#795000
0*
1&
#800000
0&
#805000
0;
1&
#810000
0&
#815000
b1001 #
b1001 6
b1 7
b10 5
b10 -
b1 .
b1001 =
1(
1&
#820000
0&
#825000
0(
b10001 ,
b10001 0
1&
#830000
0&
#835000
b1101 >
1;
1&
#840000
0&
#845000
b11 5
b100 8
b11 -
b100 /
b1101 '
b1101 1
1*
1&
#850000
0&
#855000
0*
1&
#860000
0&
#865000
0;
1&
#870000
0&
#875000
b1101 #
b1101 6
b10 7
b10 5
b10 -
b10 .
b1101 =
1(
1&
#880000
0&
#885000
0(
b10010 ,
b10010 0
1&
#890000
0&
#895000
b11101101 >
1;
1&
#900000
0&
#905000
b11 5
b101 8
b11 -
b101 /
b11101101 '
b11101101 1
1*
1&
#910000
0&
#915000
0*
1&
#920000
0&
#925000
0;
1&
#930000
0&
#935000
b1100101 #
b1100101 6
b11 7
b10 5
b10 -
b11 .
b1100101 =
1(
1&
#940000
0&
#945000
0(
b10011 ,
b10011 0
1&
#950000
0&
#955000
b11000110 >
1;
1&
#960000
0&
#965000
b11 5
b110 8
b11 -
b110 /
b11000110 '
b11000110 1
1*
1&
#970000
0&
#975000
0*
1&
#980000
0&
#985000
b10101010 >
1&
#990000
0&
#995000
b111 8
b100 5
b100 -
b111 /
b10101010 '
b10101010 1
1*
1&
#1000000
0&
#1005000
0*
1&
#1010000
0&
#1015000
b1110111 >
1&
#1020000
0&
#1025000
b101 5
b1000 8
b101 -
b1000 /
b1110111 '
b1110111 1
1*
1&
#1030000
0&
#1035000
0*
1&
#1040000
0&
#1045000
0;
1&
#1050000
0&
#1055000
b1101 #
b1101 6
b100 7
b100 5
b100 -
b100 .
b1101 =
1(
1&
#1060000
0&
#1065000
0(
b10100 ,
b10100 0
1&
#1070000
0&
#1075000
b11110010 >
1;
1&
#1080000
0&
#1085000
b101 5
b1001 8
b101 -
b1001 /
b11110010 '
b11110010 1
1*
1&
#1090000
0&
#1095000
0*
1&
#1100000
0&
#1105000
0;
1&
#1110000
0&
#1115000
b11101101 #
b11101101 6
b101 7
b100 5
b100 -
b101 .
b11101101 =
1(
1&
#1120000
0&
#1125000
0(
b10101 ,
b10101 0
1&
#1130000
0&
#1135000
1&
#1140000
0&
#1145000
b11 5
b110 7
b11000110 #
b11000110 6
b11 -
b110 .
b11000110 =
1(
1&
#1150000
0&
#1155000
0(
b10110 ,
b10110 0
1&
#1160000
0&
#1165000
b1011100 >
1;
1&
#1170000
0&
#1175000
b1010 8
b100 5
b100 -
b1010 /
b1011100 '
b1011100 1
1*
1&
#1180000
0&
#1185000
0*
1&
#1190000
0&
#1195000
b101101 >
1&
#1200000
0&
#1205000
b101 5
b1011 8
b101 -
b1011 /
b101101 '
b101101 1
1*
1&
#1210000
0&
#1215000
0*
1&
#1220000
0&
#1225000
b1100011 >
1&
#1230000
0&
#1235000
b1100 8
b110 5
b110 -
b1100 /
b1100011 '
b1100011 1
1*
1&
#1240000
0&
#1245000
0*
1&
#1250000
0&
#1255000
0;
1&
#1260000
0&
#1265000
b101 5
b111 7
b10101010 #
b10101010 6
b101 -
b111 .
b10101010 =
1(
1&
#1270000
0&
#1275000
0(
b10111 ,
b10111 0
1&
#1280000
0&
#1285000
1&
#1290000
0&
#1295000
b1110111 #
b1110111 6
b1000 7
b100 5
b100 -
b1000 .
b1110111 =
1(
1&
#1300000
0&
#1305000
0(
b11000 ,
b11000 0
1&
#1310000
0&
#1315000
1&
#1320000
0&
#1325000
b11 5
b1001 7
b11110010 #
b11110010 6
b11 -
b1001 .
b11110010 =
1(
1&
#1330000
0&
#1335000
0(
b11001 ,
b11001 0
1&
#1340000
0&
#1345000
1&
#1350000
0&
#1355000
b1011100 #
b1011100 6
b1010 7
b10 5
b10 -
b1010 .
b1011100 =
1(
1&
#1360000
0&
#1365000
0(
b11010 ,
b11010 0
1&
#1370000
0&
#1375000
b10010110 >
1;
1&
#1380000
0&
#1385000
b11 5
b1101 8
b11 -
b1101 /
b10010110 '
b10010110 1
1*
1&
#1390000
0&
#1395000
0*
1&
#1400000
0&
#1405000
b1101 >
1&
#1410000
0&
#1415000
b1110 8
b100 5
b100 -
b1110 /
b1101 '
b1101 1
1*
1&
#1420000
0&
#1425000
0*
1&
#1430000
0&
#1435000
b1101011 >
1&
#1440000
0&
#1445000
b101 5
b1111 8
b101 -
b1111 /
b1101011 '
b1101011 1
1*
1&
#1450000
0&
#1455000
0*
1&
#1460000
0&
#1465000
b10 >
1&
#1470000
0&
#1475000
b0 8
b110 5
b110 -
b0 /
b10 '
b10 1
1*
1&
#1480000
0&
#1485000
0*
1&
#1490000
0&
#1495000
0;
1&
#1500000
0&
#1505000
b101 5
b1011 7
b101101 #
b101101 6
b101 -
b1011 .
b101101 =
1(
1&
#1510000
0&
#1515000
0(
b11011 ,
b11011 0
1&
#1520000
0&
#1525000
b11001111 >
1;
1&
#1530000
0&
#1535000
b1 8
b110 5
b110 -
b1 /
b11001111 '
b11001111 1
1*
1&
#1540000
0&
#1545000
0*
1&
#1550000
0&
#1555000
b1010 >
1&
#1560000
0&
#1565000
b111 5
b10 8
b111 -
b10 /
b1010 '
b1010 1
1*
1&
#1570000
0&
#1575000
0*
1&
#1580000
0&
#1585000
0;
1&
#1590000
0&
#1595000
b1100011 #
b1100011 6
b1100 7
b110 5
b110 -
b1100 .
b1100011 =
1(
1&
#1600000
0&
#1605000
0(
b11100 ,
b11100 0
1&
#1610000
0&
#1615000
1&
#1620000
0&
#1625000
b101 5
b1101 7
b10010110 #
b10010110 6
b101 -
b1101 .
b10010110 =
1(
1&
#1630000
0&
#1635000
0(
b11101 ,
b11101 0
1&
#1640000
0&
#1645000
1&
#1650000
0&
#1655000
b1101 #
b1101 6
b1110 7
b100 5
b100 -
b1110 .
b1101 =
1(
1&
#1660000
0&
#1665000
0(
b11110 ,
b11110 0
1&
#1670000
0&
#1675000
1&
#1680000
0&
#1685000
b11 5
b1111 7
b1101011 #
b1101011 6
b11 -
b1111 .
b1101011 =
1(
1&
#1690000
0&
#1695000
0(
b11111 ,
b11111 0
1&
#1700000
0&
#1705000
b11011000 >
1;
1&
#1710000
0&
#1715000
b11 8
b100 5
b100 -
b11 /
b11011000 '
b11011000 1
1*
1&
#1720000
0&
#1725000
0*
1&
#1730000
0&
#1735000
0;
1&
#1740000
0&
#1745000
b11 5
b0 7
b10 #
b10 6
b11 -
b0 .
b10 =
1(
1&
#1750000
0&
#1755000
0(
b100000 ,
b100000 0
1&
#1760000
0&
#1765000
b11101011 >
1;
1&
#1770000
0&
#1775000
b100 8
b100 5
b100 -
b100 /
b11101011 '
b11101011 1
1*
1&
#1780000
0&
#1785000
0*
1&
#1790000
0&
#1795000
0;
1&
#1800000
0&
#1805000
b11 5
b1 7
b11001111 #
b11001111 6
b11 -
b1 .
b11001111 =
1(
1&
#1810000
0&
#1815000
0(
b100001 ,
b100001 0
1&
#1820000
0&
#1825000
1&
#1830000
0&
#1835000
b1010 #
b1010 6
b10 7
b10 5
b10 -
b10 .
b1010 =
1(
1&
#1840000
0&
#1845000
0(
b100010 ,
b100010 0
1&
#1850000
0&
#1855000
1&
#1860000
0&
#1865000
b1 5
b11 7
b11011000 #
b11011000 6
b1 -
b11 .
b11011000 =
1(
1&
#1870000
0&
#1875000
0(
b100011 ,
b100011 0
1&
#1880000
0&
#1885000
1&
#1890000
0&
#1895000
b11101011 #
b11101011 6
b100 7
1"
b0 5
b0 -
b100 .
b11101011 =
1(
1&
#1900000
0&
#1905000
0(
b100100 ,
b100100 0
1&
#1910000
0&
#1915000
1&
#1920000
0&
#1925000
1(
1&
#1930000
0&
#1935000
0(
1&
#1940000
0&
#1945000
b1110001 >
1;
1&
#1950000
0&
#1955000
b101 8
0"
b1 5
b1 -
b101 /
b1110001 '
b1110001 1
1*
1&
#1960000
0&
#1965000
0*
1&
#1970000
0&
#1975000
b1001111 >
1&
#1980000
0&
#1985000
b10 5
b110 8
b10 -
b110 /
b1001111 '
b1001111 1
1*
1&
#1990000
0&
#1995000
0*
1&
#2000000
0&
#2005000
b111010 >
1&
#2010000
0&
#2015000
b111 8
b11 5
b11 -
b111 /
b111010 '
b111010 1
1*
1&
#2020000
0&
#2025000
0*
1&
#2030000
0&
#2035000
0;
1&
#2040000
0&
#2045000
b10 5
b101 7
b1110001 #
b1110001 6
b10 -
b101 .
b1110001 =
1(
1&
#2050000
0&
#2055000
0(
b100101 ,
b100101 0
1&
#2060000
0&
#2065000
b11110001 >
1;
1&
#2070000
0&
#2075000
b1000 8
b11 5
b11 -
b1000 /
b11110001 '
b11110001 1
1*
1&
#2080000
0&
#2085000
0*
1&
#2090000
0&
#2095000
b1100010 >
1&
#2100000
0&
#2105000
b100 5
b1001 8
b100 -
b1001 /
b1100010 '
b1100010 1
1*
1&
#2110000
0&
#2115000
0*
1&
#2120000
0&
#2125000
0;
1&
#2130000
0&
#2135000
b1001111 #
b1001111 6
b110 7
b11 5
b11 -
b110 .
b1001111 =
1(
1&
#2140000
0&
#2145000
0(
b100110 ,
b100110 0
1&
#2150000
0&
#2155000
b10001111 >
1;
1&
#2160000
0&
#2165000
b100 5
b1010 8
b100 -
b1010 /
b10001111 '
b10001111 1
1*
1&
#2170000
0&
#2175000
0*
1&
#2180000
0&
#2185000
0;
1&
#2190000
0&
#2195000
b111010 #
b111010 6
b111 7
b11 5
b11 -
b111 .
b111010 =
1(
1&
#2200000
0&
#2205000
0(
b100111 ,
b100111 0
1&
#2210000
0&
#2215000
b10011111 >
1;
1&
#2220000
0&
#2225000
b100 5
b1011 8
b100 -
b1011 /
b10011111 '
b10011111 1
1*
1&
#2230000
0&
#2235000
0*
1&
#2240000
0&
#2245000
0;
1&
#2250000
0&
#2255000
b11110001 #
b11110001 6
b1000 7
b11 5
b11 -
b1000 .
b11110001 =
1(
1&
#2260000
0&
#2265000
0(
b101000 ,
b101000 0
1&
#2270000
0&
#2275000
b10001001 >
1;
1&
#2280000
0&
#2285000
b100 5
b1100 8
b100 -
b1100 /
b10001001 '
b10001001 1
1*
1&
#2290000
0&
#2295000
0*
1&
#2300000
0&
#2305000
b11010000 >
1&
#2310000
0&
#2315000
b1101 8
b101 5
b101 -
b1101 /
b11010000 '
b11010000 1
1*
1&
#2320000
0&
#2325000
0*
1&
#2330000
0&
#2335000
b1010001 >
1&
#2340000
0&
#2345000
b110 5
b1110 8
b110 -
b1110 /
b1010001 '
b1010001 1
1*
1&
#2350000
0&
#2355000
0*
1&
#2360000
0&
#2365000
0;
1&
#2370000
0&
#2375000
b1100010 #
b1100010 6
b1001 7
b101 5
b101 -
b1001 .
b1100010 =
1(
1&
#2380000
0&
#2385000
0(
b101001 ,
b101001 0
1&
#2390000
0&
#2395000
1&
#2400000
0&
#2405000
b100 5
b1010 7
b10001111 #
b10001111 6
b100 -
b1010 .
b10001111 =
1(
1&
#2410000
0&
#2415000
0(
b101010 ,
b101010 0
1&
#2420000
0&
#2425000
1&
#2430000
0&
#2435000
b10011111 #
b10011111 6
b1011 7
b11 5
b11 -
b1011 .
b10011111 =
1(
1&
#2440000
0&
